{
  "probe_id": "yahoo_20260624_093841",
  "source": "Yahoo_Finance",
  "source_type": "unofficial_api",
  "contract_status": "normalized_pass",
  "retrieved_at_utc": "2026-06-24T09:38:44.844959+00:00",
  "retrieved_at_taipei": "2026-06-24T17:38:44.844959+00:00",
  "request": {
    "url": "https://query1.finance.yahoo.com/v8/finance/chart/[symbol]",
    "method": "GET",
    "params": {},
    "headers": {
      "User-Agent": "Mozilla/5.0 (Macintosh; Intel Mac OS X 10_15_7) AppleWebKit/537.36"
    }
  },
  "http_status": 200,
  "http_ok": true,
  "parse_status": "success",
  "normalization_status": "success",
  "schema_fingerprint": {
    "type": "dict",
    "keys": [
      "chart_range",
      "coverage_status",
      "currency",
      "data_granularity",
      "data_quality_flags",
      "delay_status",
      "exchange_name",
      "exchange_timezone_name",
      "first_trade_date",
      "freshness_status",
      "gmtoffset",
      "raw_meta",
      "regular_market_price",
      "regular_market_time",
      "regular_market_time_local",
      "regular_market_time_utc",
      "requested_symbol",
      "retrieved_at_utc",
      "series",
      "source",
      "source_risk_flags",
      "source_type",
      "staleness_seconds",
      "symbol",
      "unmapped_meta_fields",
      "valid_ranges"
    ],
    "hash": "fdaa3d3a96c35478d695f1da2af55971"
  },
  "schema_hash": "fdaa3d3a96c35478d695f1da2af55971",
  "raw_sample_path": null,
  "normalized_sample_path": null,
  "raw_sample": {
    "meta": {
      "currency": "TWD",
      "symbol": "2330.TW",
      "exchangeName": "TAI",
      "fullExchangeName": "Taiwan",
      "instrumentType": "EQUITY",
      "firstTradeDate": 946947600,
      "regularMarketTime": 1782279008,
      "hasPrePostMarketData": false,
      "gmtoffset": 28800,
      "timezone": "CST",
      "exchangeTimezoneName": "Asia/Taipei",
      "regularMarketPrice": 2390.0,
      "fiftyTwoWeekHigh": 2535.0,
      "fiftyTwoWeekLow": 1055.0,
      "regularMarketDayHigh": 2445.0,
      "regularMarketDayLow": 2390.0,
      "regularMarketVolume": 65632286,
      "longName": "Taiwan Semiconductor Manufacturing Company Limited",
      "shortName": "TAIWAN SEMICONDUCTOR MANUFACTUR",
      "chartPreviousClose": 2490.0,
      "previousClose": 2490.0,
      "scale": 3,
      "priceHint": 2,
      "currentTradingPeriod": {
        "pre": {
          "timezone": "CST",
          "start": 1782262800,
          "end": 1782262800,
          "gmtoffset": 28800
        },
        "regular": {
          "timezone": "CST",
          "start": 1782262800,
          "end": 1782279000,
          "gmtoffset": 28800
        },
        "post": {
          "timezone": "CST",
          "start": 1782279000,
          "end": 1782279000,
          "gmtoffset": 28800
        }
      },
      "tradingPeriods": [
        [
          {
            "timezone": "CST",
            "start": 1782262800,
            "end": 1782279000,
            "gmtoffset": 28800
          }
        ]
      ],
      "dataGranularity": "1m",
      "range": "1d",
      "validRanges": [
        "1d",
        "5d",
        "1mo",
        "3mo",
        "6mo",
        "1y",
        "2y",
        "5y",
        "10y",
        "ytd",
        "max"
      ]
    },
    "_details": [
      {
        "symbol": "2330.TW",
        "status": 200,
        "success": true
      },
      {
        "symbol": "0050.TW",
        "status": 200,
        "success": true
      },
      {
        "symbol": "00929.TW",
        "status": 200,
        "success": true
      },
      {
        "symbol": "8069.TWO",
        "status": 200,
        "success": true
      },
      {
        "symbol": "^TWII",
        "status": 200,
        "success": true
      }
    ]
  },
  "normalized_sample": {
    "symbol": "2330.TW",
    "requested_symbol": "2330.TW",
    "source": "Yahoo_Finance",
    "source_type": "unofficial_api",
    "currency": "TWD",
    "exchange_name": "TAI",
    "exchange_timezone_name": "Asia/Taipei",
    "gmtoffset": 28800,
    "regular_market_price": 2390.0,
    "regular_market_time": 1782279008,
    "regular_market_time_utc": "2026-06-24T05:30:08+00:00",
    "regular_market_time_local": "2026-06-24T13:30:08+08:00",
    "chart_range": "1d",
    "data_granularity": "1m",
    "valid_ranges": [
      "1d",
      "5d",
      "1mo",
      "3mo",
      "6mo",
      "1y",
      "2y",
      "5y",
      "10y",
      "ytd",
      "max"
    ],
    "first_trade_date": 946947600,
    "retrieved_at_utc": "2026-06-24T09:38:41.608818+00:00",
    "staleness_seconds": 14913,
    "freshness_status": "realtime_candidate",
    "delay_status": "delayed",
    "source_risk_flags": [
      "unofficial_source",
      "rate_limits_apply",
      "no_execution_guarantees"
    ],
    "data_quality_flags": [
      "missing_adjclose_array"
    ],
    "coverage_status": "observed_supported",
    "series": {
      "timestamps": [
        1782262800,
        1782262860,
        1782262920,
        1782262980,
        1782263040,
        1782263100,
        1782263160,
        1782263220,
        1782263280,
        1782263340,
        1782263400,
        1782263460,
        1782263520,
        1782263580,
        1782263640,
        1782263700,
        1782263760,
        1782263820,
        1782263880,
        1782263940,
        1782264000,
        1782264060,
        1782264120,
        1782264180,
        1782264240,
        1782264300,
        1782264360,
        1782264420,
        1782264480,
        1782264540,
        1782264600,
        1782264660,
        1782264720,
        1782264780,
        1782264840,
        1782264900,
        1782264960,
        1782265020,
        1782265080,
        1782265140,
        1782265200,
        1782265260,
        1782265320,
        1782265380,
        1782265440,
        1782265500,
        1782265560,
        1782265620,
        1782265680,
        1782265740,
        1782265800,
        1782265860,
        1782265920,
        1782265980,
        1782266040,
        1782266100,
        1782266160,
        1782266220,
        1782266280,
        1782266340,
        1782266400,
        1782266460,
        1782266520,
        1782266580,
        1782266640,
        1782266700,
        1782266760,
        1782266820,
        1782266880,
        1782266940,
        1782267000,
        1782267060,
        1782267120,
        1782267180,
        1782267240,
        1782267300,
        1782267360,
        1782267420,
        1782267480,
        1782267540,
        1782267600,
        1782267660,
        1782267720,
        1782267780,
        1782267840,
        1782267900,
        1782267960,
        1782268020,
        1782268080,
        1782268140,
        1782268200,
        1782268260,
        1782268320,
        1782268380,
        1782268440,
        1782268500,
        1782268560,
        1782268620,
        1782268680,
        1782268740,
        1782268800,
        1782268860,
        1782268920,
        1782268980,
        1782269040,
        1782269100,
        1782269160,
        1782269220,
        1782269280,
        1782269340,
        1782269400,
        1782269460,
        1782269520,
        1782269580,
        1782269640,
        1782269700,
        1782269760,
        1782269820,
        1782269880,
        1782269940,
        1782270000,
        1782270060,
        1782270120,
        1782270180,
        1782270240,
        1782270300,
        1782270360,
        1782270420,
        1782270480,
        1782270540,
        1782270600,
        1782270660,
        1782270720,
        1782270780,
        1782270840,
        1782270900,
        1782270960,
        1782271020,
        1782271080,
        1782271140,
        1782271200,
        1782271260,
        1782271320,
        1782271380,
        1782271440,
        1782271500,
        1782271560,
        1782271620,
        1782271680,
        1782271740,
        1782271800,
        1782271860,
        1782271920,
        1782271980,
        1782272040,
        1782272100,
        1782272160,
        1782272220,
        1782272280,
        1782272340,
        1782272400,
        1782272460,
        1782272520,
        1782272580,
        1782272640,
        1782272700,
        1782272760,
        1782272820,
        1782272880,
        1782272940,
        1782273000,
        1782273060,
        1782273120,
        1782273180,
        1782273240,
        1782273300,
        1782273360,
        1782273420,
        1782273480,
        1782273540,
        1782273600,
        1782273660,
        1782273720,
        1782273780,
        1782273840,
        1782273900,
        1782273960,
        1782274020,
        1782274080,
        1782274140,
        1782274200,
        1782274260,
        1782274320,
        1782274380,
        1782274440,
        1782274500,
        1782274560,
        1782274620,
        1782274680,
        1782274740,
        1782274800,
        1782274860,
        1782274920,
        1782274980,
        1782275040,
        1782275100,
        1782275160,
        1782275220,
        1782275280,
        1782275340,
        1782275400,
        1782275460,
        1782275520,
        1782275580,
        1782275640,
        1782275700,
        1782275760,
        1782275820,
        1782275880,
        1782275940,
        1782276000,
        1782276060,
        1782276120,
        1782276180,
        1782276240,
        1782276300,
        1782276360,
        1782276420,
        1782276480,
        1782276540,
        1782276600,
        1782276660,
        1782276720,
        1782276780,
        1782276840,
        1782276900,
        1782276960,
        1782277020,
        1782277080,
        1782277140,
        1782277200,
        1782277260,
        1782277320,
        1782277380,
        1782277440,
        1782277500,
        1782277560,
        1782277620,
        1782277680,
        1782277740,
        1782277800,
        1782277860,
        1782277920,
        1782277980,
        1782278040,
        1782278100,
        1782278160,
        1782278220,
        1782278280,
        1782278340,
        1782278400,
        1782278460,
        1782278520,
        1782278580,
        1782278640,
        1782278700,
        1782278760,
        1782278820,
        1782278880,
        1782278940,
        1782279000
      ],
      "timestamps_utc": [
        "2026-06-24T01:00:00+00:00",
        "2026-06-24T01:01:00+00:00",
        "2026-06-24T01:02:00+00:00",
        "2026-06-24T01:03:00+00:00",
        "2026-06-24T01:04:00+00:00",
        "2026-06-24T01:05:00+00:00",
        "2026-06-24T01:06:00+00:00",
        "2026-06-24T01:07:00+00:00",
        "2026-06-24T01:08:00+00:00",
        "2026-06-24T01:09:00+00:00",
        "2026-06-24T01:10:00+00:00",
        "2026-06-24T01:11:00+00:00",
        "2026-06-24T01:12:00+00:00",
        "2026-06-24T01:13:00+00:00",
        "2026-06-24T01:14:00+00:00",
        "2026-06-24T01:15:00+00:00",
        "2026-06-24T01:16:00+00:00",
        "2026-06-24T01:17:00+00:00",
        "2026-06-24T01:18:00+00:00",
        "2026-06-24T01:19:00+00:00",
        "2026-06-24T01:20:00+00:00",
        "2026-06-24T01:21:00+00:00",
        "2026-06-24T01:22:00+00:00",
        "2026-06-24T01:23:00+00:00",
        "2026-06-24T01:24:00+00:00",
        "2026-06-24T01:25:00+00:00",
        "2026-06-24T01:26:00+00:00",
        "2026-06-24T01:27:00+00:00",
        "2026-06-24T01:28:00+00:00",
        "2026-06-24T01:29:00+00:00",
        "2026-06-24T01:30:00+00:00",
        "2026-06-24T01:31:00+00:00",
        "2026-06-24T01:32:00+00:00",
        "2026-06-24T01:33:00+00:00",
        "2026-06-24T01:34:00+00:00",
        "2026-06-24T01:35:00+00:00",
        "2026-06-24T01:36:00+00:00",
        "2026-06-24T01:37:00+00:00",
        "2026-06-24T01:38:00+00:00",
        "2026-06-24T01:39:00+00:00",
        "2026-06-24T01:40:00+00:00",
        "2026-06-24T01:41:00+00:00",
        "2026-06-24T01:42:00+00:00",
        "2026-06-24T01:43:00+00:00",
        "2026-06-24T01:44:00+00:00",
        "2026-06-24T01:45:00+00:00",
        "2026-06-24T01:46:00+00:00",
        "2026-06-24T01:47:00+00:00",
        "2026-06-24T01:48:00+00:00",
        "2026-06-24T01:49:00+00:00",
        "2026-06-24T01:50:00+00:00",
        "2026-06-24T01:51:00+00:00",
        "2026-06-24T01:52:00+00:00",
        "2026-06-24T01:53:00+00:00",
        "2026-06-24T01:54:00+00:00",
        "2026-06-24T01:55:00+00:00",
        "2026-06-24T01:56:00+00:00",
        "2026-06-24T01:57:00+00:00",
        "2026-06-24T01:58:00+00:00",
        "2026-06-24T01:59:00+00:00",
        "2026-06-24T02:00:00+00:00",
        "2026-06-24T02:01:00+00:00",
        "2026-06-24T02:02:00+00:00",
        "2026-06-24T02:03:00+00:00",
        "2026-06-24T02:04:00+00:00",
        "2026-06-24T02:05:00+00:00",
        "2026-06-24T02:06:00+00:00",
        "2026-06-24T02:07:00+00:00",
        "2026-06-24T02:08:00+00:00",
        "2026-06-24T02:09:00+00:00",
        "2026-06-24T02:10:00+00:00",
        "2026-06-24T02:11:00+00:00",
        "2026-06-24T02:12:00+00:00",
        "2026-06-24T02:13:00+00:00",
        "2026-06-24T02:14:00+00:00",
        "2026-06-24T02:15:00+00:00",
        "2026-06-24T02:16:00+00:00",
        "2026-06-24T02:17:00+00:00",
        "2026-06-24T02:18:00+00:00",
        "2026-06-24T02:19:00+00:00",
        "2026-06-24T02:20:00+00:00",
        "2026-06-24T02:21:00+00:00",
        "2026-06-24T02:22:00+00:00",
        "2026-06-24T02:23:00+00:00",
        "2026-06-24T02:24:00+00:00",
        "2026-06-24T02:25:00+00:00",
        "2026-06-24T02:26:00+00:00",
        "2026-06-24T02:27:00+00:00",
        "2026-06-24T02:28:00+00:00",
        "2026-06-24T02:29:00+00:00",
        "2026-06-24T02:30:00+00:00",
        "2026-06-24T02:31:00+00:00",
        "2026-06-24T02:32:00+00:00",
        "2026-06-24T02:33:00+00:00",
        "2026-06-24T02:34:00+00:00",
        "2026-06-24T02:35:00+00:00",
        "2026-06-24T02:36:00+00:00",
        "2026-06-24T02:37:00+00:00",
        "2026-06-24T02:38:00+00:00",
        "2026-06-24T02:39:00+00:00",
        "2026-06-24T02:40:00+00:00",
        "2026-06-24T02:41:00+00:00",
        "2026-06-24T02:42:00+00:00",
        "2026-06-24T02:43:00+00:00",
        "2026-06-24T02:44:00+00:00",
        "2026-06-24T02:45:00+00:00",
        "2026-06-24T02:46:00+00:00",
        "2026-06-24T02:47:00+00:00",
        "2026-06-24T02:48:00+00:00",
        "2026-06-24T02:49:00+00:00",
        "2026-06-24T02:50:00+00:00",
        "2026-06-24T02:51:00+00:00",
        "2026-06-24T02:52:00+00:00",
        "2026-06-24T02:53:00+00:00",
        "2026-06-24T02:54:00+00:00",
        "2026-06-24T02:55:00+00:00",
        "2026-06-24T02:56:00+00:00",
        "2026-06-24T02:57:00+00:00",
        "2026-06-24T02:58:00+00:00",
        "2026-06-24T02:59:00+00:00",
        "2026-06-24T03:00:00+00:00",
        "2026-06-24T03:01:00+00:00",
        "2026-06-24T03:02:00+00:00",
        "2026-06-24T03:03:00+00:00",
        "2026-06-24T03:04:00+00:00",
        "2026-06-24T03:05:00+00:00",
        "2026-06-24T03:06:00+00:00",
        "2026-06-24T03:07:00+00:00",
        "2026-06-24T03:08:00+00:00",
        "2026-06-24T03:09:00+00:00",
        "2026-06-24T03:10:00+00:00",
        "2026-06-24T03:11:00+00:00",
        "2026-06-24T03:12:00+00:00",
        "2026-06-24T03:13:00+00:00",
        "2026-06-24T03:14:00+00:00",
        "2026-06-24T03:15:00+00:00",
        "2026-06-24T03:16:00+00:00",
        "2026-06-24T03:17:00+00:00",
        "2026-06-24T03:18:00+00:00",
        "2026-06-24T03:19:00+00:00",
        "2026-06-24T03:20:00+00:00",
        "2026-06-24T03:21:00+00:00",
        "2026-06-24T03:22:00+00:00",
        "2026-06-24T03:23:00+00:00",
        "2026-06-24T03:24:00+00:00",
        "2026-06-24T03:25:00+00:00",
        "2026-06-24T03:26:00+00:00",
        "2026-06-24T03:27:00+00:00",
        "2026-06-24T03:28:00+00:00",
        "2026-06-24T03:29:00+00:00",
        "2026-06-24T03:30:00+00:00",
        "2026-06-24T03:31:00+00:00",
        "2026-06-24T03:32:00+00:00",
        "2026-06-24T03:33:00+00:00",
        "2026-06-24T03:34:00+00:00",
        "2026-06-24T03:35:00+00:00",
        "2026-06-24T03:36:00+00:00",
        "2026-06-24T03:37:00+00:00",
        "2026-06-24T03:38:00+00:00",
        "2026-06-24T03:39:00+00:00",
        "2026-06-24T03:40:00+00:00",
        "2026-06-24T03:41:00+00:00",
        "2026-06-24T03:42:00+00:00",
        "2026-06-24T03:43:00+00:00",
        "2026-06-24T03:44:00+00:00",
        "2026-06-24T03:45:00+00:00",
        "2026-06-24T03:46:00+00:00",
        "2026-06-24T03:47:00+00:00",
        "2026-06-24T03:48:00+00:00",
        "2026-06-24T03:49:00+00:00",
        "2026-06-24T03:50:00+00:00",
        "2026-06-24T03:51:00+00:00",
        "2026-06-24T03:52:00+00:00",
        "2026-06-24T03:53:00+00:00",
        "2026-06-24T03:54:00+00:00",
        "2026-06-24T03:55:00+00:00",
        "2026-06-24T03:56:00+00:00",
        "2026-06-24T03:57:00+00:00",
        "2026-06-24T03:58:00+00:00",
        "2026-06-24T03:59:00+00:00",
        "2026-06-24T04:00:00+00:00",
        "2026-06-24T04:01:00+00:00",
        "2026-06-24T04:02:00+00:00",
        "2026-06-24T04:03:00+00:00",
        "2026-06-24T04:04:00+00:00",
        "2026-06-24T04:05:00+00:00",
        "2026-06-24T04:06:00+00:00",
        "2026-06-24T04:07:00+00:00",
        "2026-06-24T04:08:00+00:00",
        "2026-06-24T04:09:00+00:00",
        "2026-06-24T04:10:00+00:00",
        "2026-06-24T04:11:00+00:00",
        "2026-06-24T04:12:00+00:00",
        "2026-06-24T04:13:00+00:00",
        "2026-06-24T04:14:00+00:00",
        "2026-06-24T04:15:00+00:00",
        "2026-06-24T04:16:00+00:00",
        "2026-06-24T04:17:00+00:00",
        "2026-06-24T04:18:00+00:00",
        "2026-06-24T04:19:00+00:00",
        "2026-06-24T04:20:00+00:00",
        "2026-06-24T04:21:00+00:00",
        "2026-06-24T04:22:00+00:00",
        "2026-06-24T04:23:00+00:00",
        "2026-06-24T04:24:00+00:00",
        "2026-06-24T04:25:00+00:00",
        "2026-06-24T04:26:00+00:00",
        "2026-06-24T04:27:00+00:00",
        "2026-06-24T04:28:00+00:00",
        "2026-06-24T04:29:00+00:00",
        "2026-06-24T04:30:00+00:00",
        "2026-06-24T04:31:00+00:00",
        "2026-06-24T04:32:00+00:00",
        "2026-06-24T04:33:00+00:00",
        "2026-06-24T04:34:00+00:00",
        "2026-06-24T04:35:00+00:00",
        "2026-06-24T04:36:00+00:00",
        "2026-06-24T04:37:00+00:00",
        "2026-06-24T04:38:00+00:00",
        "2026-06-24T04:39:00+00:00",
        "2026-06-24T04:40:00+00:00",
        "2026-06-24T04:41:00+00:00",
        "2026-06-24T04:42:00+00:00",
        "2026-06-24T04:43:00+00:00",
        "2026-06-24T04:44:00+00:00",
        "2026-06-24T04:45:00+00:00",
        "2026-06-24T04:46:00+00:00",
        "2026-06-24T04:47:00+00:00",
        "2026-06-24T04:48:00+00:00",
        "2026-06-24T04:49:00+00:00",
        "2026-06-24T04:50:00+00:00",
        "2026-06-24T04:51:00+00:00",
        "2026-06-24T04:52:00+00:00",
        "2026-06-24T04:53:00+00:00",
        "2026-06-24T04:54:00+00:00",
        "2026-06-24T04:55:00+00:00",
        "2026-06-24T04:56:00+00:00",
        "2026-06-24T04:57:00+00:00",
        "2026-06-24T04:58:00+00:00",
        "2026-06-24T04:59:00+00:00",
        "2026-06-24T05:00:00+00:00",
        "2026-06-24T05:01:00+00:00",
        "2026-06-24T05:02:00+00:00",
        "2026-06-24T05:03:00+00:00",
        "2026-06-24T05:04:00+00:00",
        "2026-06-24T05:05:00+00:00",
        "2026-06-24T05:06:00+00:00",
        "2026-06-24T05:07:00+00:00",
        "2026-06-24T05:08:00+00:00",
        "2026-06-24T05:09:00+00:00",
        "2026-06-24T05:10:00+00:00",
        "2026-06-24T05:11:00+00:00",
        "2026-06-24T05:12:00+00:00",
        "2026-06-24T05:13:00+00:00",
        "2026-06-24T05:14:00+00:00",
        "2026-06-24T05:15:00+00:00",
        "2026-06-24T05:16:00+00:00",
        "2026-06-24T05:17:00+00:00",
        "2026-06-24T05:18:00+00:00",
        "2026-06-24T05:19:00+00:00",
        "2026-06-24T05:20:00+00:00",
        "2026-06-24T05:21:00+00:00",
        "2026-06-24T05:22:00+00:00",
        "2026-06-24T05:23:00+00:00",
        "2026-06-24T05:24:00+00:00",
        "2026-06-24T05:25:00+00:00",
        "2026-06-24T05:26:00+00:00",
        "2026-06-24T05:27:00+00:00",
        "2026-06-24T05:28:00+00:00",
        "2026-06-24T05:29:00+00:00",
        "2026-06-24T05:30:00+00:00"
      ],
      "timestamps_local": [
        "2026-06-24T09:00:00+08:00",
        "2026-06-24T09:01:00+08:00",
        "2026-06-24T09:02:00+08:00",
        "2026-06-24T09:03:00+08:00",
        "2026-06-24T09:04:00+08:00",
        "2026-06-24T09:05:00+08:00",
        "2026-06-24T09:06:00+08:00",
        "2026-06-24T09:07:00+08:00",
        "2026-06-24T09:08:00+08:00",
        "2026-06-24T09:09:00+08:00",
        "2026-06-24T09:10:00+08:00",
        "2026-06-24T09:11:00+08:00",
        "2026-06-24T09:12:00+08:00",
        "2026-06-24T09:13:00+08:00",
        "2026-06-24T09:14:00+08:00",
        "2026-06-24T09:15:00+08:00",
        "2026-06-24T09:16:00+08:00",
        "2026-06-24T09:17:00+08:00",
        "2026-06-24T09:18:00+08:00",
        "2026-06-24T09:19:00+08:00",
        "2026-06-24T09:20:00+08:00",
        "2026-06-24T09:21:00+08:00",
        "2026-06-24T09:22:00+08:00",
        "2026-06-24T09:23:00+08:00",
        "2026-06-24T09:24:00+08:00",
        "2026-06-24T09:25:00+08:00",
        "2026-06-24T09:26:00+08:00",
        "2026-06-24T09:27:00+08:00",
        "2026-06-24T09:28:00+08:00",
        "2026-06-24T09:29:00+08:00",
        "2026-06-24T09:30:00+08:00",
        "2026-06-24T09:31:00+08:00",
        "2026-06-24T09:32:00+08:00",
        "2026-06-24T09:33:00+08:00",
        "2026-06-24T09:34:00+08:00",
        "2026-06-24T09:35:00+08:00",
        "2026-06-24T09:36:00+08:00",
        "2026-06-24T09:37:00+08:00",
        "2026-06-24T09:38:00+08:00",
        "2026-06-24T09:39:00+08:00",
        "2026-06-24T09:40:00+08:00",
        "2026-06-24T09:41:00+08:00",
        "2026-06-24T09:42:00+08:00",
        "2026-06-24T09:43:00+08:00",
        "2026-06-24T09:44:00+08:00",
        "2026-06-24T09:45:00+08:00",
        "2026-06-24T09:46:00+08:00",
        "2026-06-24T09:47:00+08:00",
        "2026-06-24T09:48:00+08:00",
        "2026-06-24T09:49:00+08:00",
        "2026-06-24T09:50:00+08:00",
        "2026-06-24T09:51:00+08:00",
        "2026-06-24T09:52:00+08:00",
        "2026-06-24T09:53:00+08:00",
        "2026-06-24T09:54:00+08:00",
        "2026-06-24T09:55:00+08:00",
        "2026-06-24T09:56:00+08:00",
        "2026-06-24T09:57:00+08:00",
        "2026-06-24T09:58:00+08:00",
        "2026-06-24T09:59:00+08:00",
        "2026-06-24T10:00:00+08:00",
        "2026-06-24T10:01:00+08:00",
        "2026-06-24T10:02:00+08:00",
        "2026-06-24T10:03:00+08:00",
        "2026-06-24T10:04:00+08:00",
        "2026-06-24T10:05:00+08:00",
        "2026-06-24T10:06:00+08:00",
        "2026-06-24T10:07:00+08:00",
        "2026-06-24T10:08:00+08:00",
        "2026-06-24T10:09:00+08:00",
        "2026-06-24T10:10:00+08:00",
        "2026-06-24T10:11:00+08:00",
        "2026-06-24T10:12:00+08:00",
        "2026-06-24T10:13:00+08:00",
        "2026-06-24T10:14:00+08:00",
        "2026-06-24T10:15:00+08:00",
        "2026-06-24T10:16:00+08:00",
        "2026-06-24T10:17:00+08:00",
        "2026-06-24T10:18:00+08:00",
        "2026-06-24T10:19:00+08:00",
        "2026-06-24T10:20:00+08:00",
        "2026-06-24T10:21:00+08:00",
        "2026-06-24T10:22:00+08:00",
        "2026-06-24T10:23:00+08:00",
        "2026-06-24T10:24:00+08:00",
        "2026-06-24T10:25:00+08:00",
        "2026-06-24T10:26:00+08:00",
        "2026-06-24T10:27:00+08:00",
        "2026-06-24T10:28:00+08:00",
        "2026-06-24T10:29:00+08:00",
        "2026-06-24T10:30:00+08:00",
        "2026-06-24T10:31:00+08:00",
        "2026-06-24T10:32:00+08:00",
        "2026-06-24T10:33:00+08:00",
        "2026-06-24T10:34:00+08:00",
        "2026-06-24T10:35:00+08:00",
        "2026-06-24T10:36:00+08:00",
        "2026-06-24T10:37:00+08:00",
        "2026-06-24T10:38:00+08:00",
        "2026-06-24T10:39:00+08:00",
        "2026-06-24T10:40:00+08:00",
        "2026-06-24T10:41:00+08:00",
        "2026-06-24T10:42:00+08:00",
        "2026-06-24T10:43:00+08:00",
        "2026-06-24T10:44:00+08:00",
        "2026-06-24T10:45:00+08:00",
        "2026-06-24T10:46:00+08:00",
        "2026-06-24T10:47:00+08:00",
        "2026-06-24T10:48:00+08:00",
        "2026-06-24T10:49:00+08:00",
        "2026-06-24T10:50:00+08:00",
        "2026-06-24T10:51:00+08:00",
        "2026-06-24T10:52:00+08:00",
        "2026-06-24T10:53:00+08:00",
        "2026-06-24T10:54:00+08:00",
        "2026-06-24T10:55:00+08:00",
        "2026-06-24T10:56:00+08:00",
        "2026-06-24T10:57:00+08:00",
        "2026-06-24T10:58:00+08:00",
        "2026-06-24T10:59:00+08:00",
        "2026-06-24T11:00:00+08:00",
        "2026-06-24T11:01:00+08:00",
        "2026-06-24T11:02:00+08:00",
        "2026-06-24T11:03:00+08:00",
        "2026-06-24T11:04:00+08:00",
        "2026-06-24T11:05:00+08:00",
        "2026-06-24T11:06:00+08:00",
        "2026-06-24T11:07:00+08:00",
        "2026-06-24T11:08:00+08:00",
        "2026-06-24T11:09:00+08:00",
        "2026-06-24T11:10:00+08:00",
        "2026-06-24T11:11:00+08:00",
        "2026-06-24T11:12:00+08:00",
        "2026-06-24T11:13:00+08:00",
        "2026-06-24T11:14:00+08:00",
        "2026-06-24T11:15:00+08:00",
        "2026-06-24T11:16:00+08:00",
        "2026-06-24T11:17:00+08:00",
        "2026-06-24T11:18:00+08:00",
        "2026-06-24T11:19:00+08:00",
        "2026-06-24T11:20:00+08:00",
        "2026-06-24T11:21:00+08:00",
        "2026-06-24T11:22:00+08:00",
        "2026-06-24T11:23:00+08:00",
        "2026-06-24T11:24:00+08:00",
        "2026-06-24T11:25:00+08:00",
        "2026-06-24T11:26:00+08:00",
        "2026-06-24T11:27:00+08:00",
        "2026-06-24T11:28:00+08:00",
        "2026-06-24T11:29:00+08:00",
        "2026-06-24T11:30:00+08:00",
        "2026-06-24T11:31:00+08:00",
        "2026-06-24T11:32:00+08:00",
        "2026-06-24T11:33:00+08:00",
        "2026-06-24T11:34:00+08:00",
        "2026-06-24T11:35:00+08:00",
        "2026-06-24T11:36:00+08:00",
        "2026-06-24T11:37:00+08:00",
        "2026-06-24T11:38:00+08:00",
        "2026-06-24T11:39:00+08:00",
        "2026-06-24T11:40:00+08:00",
        "2026-06-24T11:41:00+08:00",
        "2026-06-24T11:42:00+08:00",
        "2026-06-24T11:43:00+08:00",
        "2026-06-24T11:44:00+08:00",
        "2026-06-24T11:45:00+08:00",
        "2026-06-24T11:46:00+08:00",
        "2026-06-24T11:47:00+08:00",
        "2026-06-24T11:48:00+08:00",
        "2026-06-24T11:49:00+08:00",
        "2026-06-24T11:50:00+08:00",
        "2026-06-24T11:51:00+08:00",
        "2026-06-24T11:52:00+08:00",
        "2026-06-24T11:53:00+08:00",
        "2026-06-24T11:54:00+08:00",
        "2026-06-24T11:55:00+08:00",
        "2026-06-24T11:56:00+08:00",
        "2026-06-24T11:57:00+08:00",
        "2026-06-24T11:58:00+08:00",
        "2026-06-24T11:59:00+08:00",
        "2026-06-24T12:00:00+08:00",
        "2026-06-24T12:01:00+08:00",
        "2026-06-24T12:02:00+08:00",
        "2026-06-24T12:03:00+08:00",
        "2026-06-24T12:04:00+08:00",
        "2026-06-24T12:05:00+08:00",
        "2026-06-24T12:06:00+08:00",
        "2026-06-24T12:07:00+08:00",
        "2026-06-24T12:08:00+08:00",
        "2026-06-24T12:09:00+08:00",
        "2026-06-24T12:10:00+08:00",
        "2026-06-24T12:11:00+08:00",
        "2026-06-24T12:12:00+08:00",
        "2026-06-24T12:13:00+08:00",
        "2026-06-24T12:14:00+08:00",
        "2026-06-24T12:15:00+08:00",
        "2026-06-24T12:16:00+08:00",
        "2026-06-24T12:17:00+08:00",
        "2026-06-24T12:18:00+08:00",
        "2026-06-24T12:19:00+08:00",
        "2026-06-24T12:20:00+08:00",
        "2026-06-24T12:21:00+08:00",
        "2026-06-24T12:22:00+08:00",
        "2026-06-24T12:23:00+08:00",
        "2026-06-24T12:24:00+08:00",
        "2026-06-24T12:25:00+08:00",
        "2026-06-24T12:26:00+08:00",
        "2026-06-24T12:27:00+08:00",
        "2026-06-24T12:28:00+08:00",
        "2026-06-24T12:29:00+08:00",
        "2026-06-24T12:30:00+08:00",
        "2026-06-24T12:31:00+08:00",
        "2026-06-24T12:32:00+08:00",
        "2026-06-24T12:33:00+08:00",
        "2026-06-24T12:34:00+08:00",
        "2026-06-24T12:35:00+08:00",
        "2026-06-24T12:36:00+08:00",
        "2026-06-24T12:37:00+08:00",
        "2026-06-24T12:38:00+08:00",
        "2026-06-24T12:39:00+08:00",
        "2026-06-24T12:40:00+08:00",
        "2026-06-24T12:41:00+08:00",
        "2026-06-24T12:42:00+08:00",
        "2026-06-24T12:43:00+08:00",
        "2026-06-24T12:44:00+08:00",
        "2026-06-24T12:45:00+08:00",
        "2026-06-24T12:46:00+08:00",
        "2026-06-24T12:47:00+08:00",
        "2026-06-24T12:48:00+08:00",
        "2026-06-24T12:49:00+08:00",
        "2026-06-24T12:50:00+08:00",
        "2026-06-24T12:51:00+08:00",
        "2026-06-24T12:52:00+08:00",
        "2026-06-24T12:53:00+08:00",
        "2026-06-24T12:54:00+08:00",
        "2026-06-24T12:55:00+08:00",
        "2026-06-24T12:56:00+08:00",
        "2026-06-24T12:57:00+08:00",
        "2026-06-24T12:58:00+08:00",
        "2026-06-24T12:59:00+08:00",
        "2026-06-24T13:00:00+08:00",
        "2026-06-24T13:01:00+08:00",
        "2026-06-24T13:02:00+08:00",
        "2026-06-24T13:03:00+08:00",
        "2026-06-24T13:04:00+08:00",
        "2026-06-24T13:05:00+08:00",
        "2026-06-24T13:06:00+08:00",
        "2026-06-24T13:07:00+08:00",
        "2026-06-24T13:08:00+08:00",
        "2026-06-24T13:09:00+08:00",
        "2026-06-24T13:10:00+08:00",
        "2026-06-24T13:11:00+08:00",
        "2026-06-24T13:12:00+08:00",
        "2026-06-24T13:13:00+08:00",
        "2026-06-24T13:14:00+08:00",
        "2026-06-24T13:15:00+08:00",
        "2026-06-24T13:16:00+08:00",
        "2026-06-24T13:17:00+08:00",
        "2026-06-24T13:18:00+08:00",
        "2026-06-24T13:19:00+08:00",
        "2026-06-24T13:20:00+08:00",
        "2026-06-24T13:21:00+08:00",
        "2026-06-24T13:22:00+08:00",
        "2026-06-24T13:23:00+08:00",
        "2026-06-24T13:24:00+08:00",
        "2026-06-24T13:25:00+08:00",
        "2026-06-24T13:26:00+08:00",
        "2026-06-24T13:27:00+08:00",
        "2026-06-24T13:28:00+08:00",
        "2026-06-24T13:29:00+08:00",
        "2026-06-24T13:30:00+08:00"
      ],
      "open": [
        2435.0,
        2445.0,
        2440.0,
        2435.0,
        2440.0,
        2435.0,
        2430.0,
        2435.0,
        2435.0,
        2435.0,
        2430.0,
        2430.0,
        2435.0,
        2435.0,
        2435.0,
        2430.0,
        2435.0,
        2435.0,
        2435.0,
        2435.0,
        2430.0,
        2425.0,
        2430.0,
        2430.0,
        2430.0,
        2430.0,
        2430.0,
        2435.0,
        2430.0,
        2430.0,
        2425.0,
        2430.0,
        2430.0,
        2430.0,
        2425.0,
        2430.0,
        2430.0,
        2430.0,
        2430.0,
        2430.0,
        2425.0,
        2420.0,
        2420.0,
        2425.0,
        2420.0,
        2420.0,
        2420.0,
        2415.0,
        2415.0,
        2420.0,
        2430.0,
        2430.0,
        2430.0,
        2430.0,
        2430.0,
        2430.0,
        2435.0,
        2430.0,
        2435.0,
        2430.0,
        2435.0,
        2435.0,
        2435.0,
        2435.0,
        2430.0,
        2425.0,
        2430.0,
        2425.0,
        2425.0,
        2425.0,
        2425.0,
        2420.0,
        2425.0,
        2425.0,
        2425.0,
        2420.0,
        2425.0,
        2425.0,
        2420.0,
        2420.0,
        2420.0,
        2420.0,
        2420.0,
        2420.0,
        2420.0,
        2420.0,
        2420.0,
        2415.0,
        2420.0,
        2420.0,
        2425.0,
        2425.0,
        2425.0,
        2420.0,
        2420.0,
        2425.0,
        2425.0,
        2420.0,
        2420.0,
        2420.0,
        2420.0,
        2420.0,
        2415.0,
        2420.0,
        2420.0,
        2420.0,
        2420.0,
        2415.0,
        2415.0,
        2415.0,
        2410.0,
        2410.0,
        2410.0,
        2410.0,
        2410.0,
        2410.0,
        2410.0,
        2415.0,
        2410.0,
        2410.0,
        2410.0,
        2410.0,
        2410.0,
        2410.0,
        2405.0,
        2410.0,
        2405.0,
        2405.0,
        2405.0,
        2405.0,
        2410.0,
        2410.0,
        2415.0,
        2415.0,
        2410.0,
        2410.0,
        2410.0,
        2415.0,
        2415.0,
        2415.0,
        2410.0,
        2410.0,
        2410.0,
        2410.0,
        2410.0,
        2410.0,
        2410.0,
        2410.0,
        2410.0,
        2415.0,
        2415.0,
        2410.0,
        2410.0,
        2410.0,
        2415.0,
        2410.0,
        2410.0,
        2410.0,
        2410.0,
        2410.0,
        2410.0,
        2410.0,
        2410.0,
        2410.0,
        2410.0,
        2410.0,
        2410.0,
        2415.0,
        2410.0,
        2410.0,
        2410.0,
        2410.0,
        2410.0,
        2410.0,
        2410.0,
        2410.0,
        2415.0,
        2410.0,
        2415.0,
        2410.0,
        2410.0,
        2410.0,
        2410.0,
        2410.0,
        2410.0,
        2410.0,
        2405.0,
        2410.0,
        2405.0,
        2405.0,
        2405.0,
        2410.0,
        2405.0,
        2410.0,
        2405.0,
        2405.0,
        2405.0,
        2410.0,
        2405.0,
        2410.0,
        2405.0,
        2405.0,
        2405.0,
        2405.0,
        2405.0,
        2405.0,
        2405.0,
        2410.0,
        2405.0,
        2400.0,
        2400.0,
        2400.0,
        2400.0,
        2400.0,
        2400.0,
        2400.0,
        2405.0,
        2410.0,
        2410.0,
        2415.0,
        2415.0,
        2410.0,
        2420.0,
        2420.0,
        2420.0,
        2420.0,
        2420.0,
        2415.0,
        2420.0,
        2415.0,
        2410.0,
        2415.0,
        2415.0,
        2415.0,
        2415.0,
        2415.0,
        2415.0,
        2415.0,
        2415.0,
        2410.0,
        2415.0,
        2410.0,
        2410.0,
        2410.0,
        2410.0,
        2410.0,
        2410.0,
        2410.0,
        2410.0,
        2410.0,
        2410.0,
        2405.0,
        2405.0,
        2410.0,
        2405.0,
        2405.0,
        2410.0,
        2405.0,
        2405.0,
        2405.0,
        2410.0,
        2405.0,
        2405.0,
        2405.0,
        2410.0,
        null,
        null,
        null,
        null,
        null,
        2390.0
      ],
      "high": [
        2445.0,
        2445.0,
        2440.0,
        2440.0,
        2440.0,
        2440.0,
        2435.0,
        2435.0,
        2435.0,
        2440.0,
        2440.0,
        2435.0,
        2435.0,
        2435.0,
        2435.0,
        2435.0,
        2435.0,
        2435.0,
        2435.0,
        2435.0,
        2435.0,
        2430.0,
        2430.0,
        2430.0,
        2435.0,
        2435.0,
        2435.0,
        2435.0,
        2435.0,
        2430.0,
        2430.0,
        2430.0,
        2430.0,
        2430.0,
        2430.0,
        2430.0,
        2430.0,
        2430.0,
        2430.0,
        2430.0,
        2430.0,
        2425.0,
        2425.0,
        2425.0,
        2425.0,
        2425.0,
        2420.0,
        2420.0,
        2420.0,
        2430.0,
        2430.0,
        2430.0,
        2430.0,
        2430.0,
        2435.0,
        2435.0,
        2435.0,
        2435.0,
        2435.0,
        2435.0,
        2435.0,
        2435.0,
        2435.0,
        2435.0,
        2435.0,
        2430.0,
        2430.0,
        2430.0,
        2425.0,
        2425.0,
        2425.0,
        2425.0,
        2425.0,
        2425.0,
        2425.0,
        2425.0,
        2425.0,
        2425.0,
        2425.0,
        2425.0,
        2425.0,
        2425.0,
        2425.0,
        2425.0,
        2425.0,
        2425.0,
        2425.0,
        2420.0,
        2425.0,
        2425.0,
        2425.0,
        2425.0,
        2425.0,
        2425.0,
        2425.0,
        2425.0,
        2425.0,
        2425.0,
        2425.0,
        2425.0,
        2425.0,
        2425.0,
        2420.0,
        2420.0,
        2420.0,
        2420.0,
        2420.0,
        2420.0,
        2420.0,
        2420.0,
        2415.0,
        2415.0,
        2415.0,
        2415.0,
        2415.0,
        2415.0,
        2415.0,
        2415.0,
        2415.0,
        2415.0,
        2415.0,
        2415.0,
        2415.0,
        2410.0,
        2410.0,
        2410.0,
        2410.0,
        2410.0,
        2410.0,
        2410.0,
        2415.0,
        2415.0,
        2415.0,
        2415.0,
        2415.0,
        2415.0,
        2415.0,
        2415.0,
        2415.0,
        2415.0,
        2415.0,
        2415.0,
        2410.0,
        2415.0,
        2415.0,
        2415.0,
        2415.0,
        2415.0,
        2415.0,
        2415.0,
        2415.0,
        2415.0,
        2415.0,
        2415.0,
        2415.0,
        2415.0,
        2415.0,
        2415.0,
        2415.0,
        2415.0,
        2415.0,
        2415.0,
        2415.0,
        2415.0,
        2415.0,
        2415.0,
        2415.0,
        2415.0,
        2415.0,
        2415.0,
        2415.0,
        2415.0,
        2415.0,
        2415.0,
        2415.0,
        2415.0,
        2415.0,
        2415.0,
        2415.0,
        2415.0,
        2415.0,
        2415.0,
        2415.0,
        2415.0,
        2415.0,
        2415.0,
        2410.0,
        2410.0,
        2410.0,
        2410.0,
        2410.0,
        2410.0,
        2410.0,
        2410.0,
        2410.0,
        2410.0,
        2410.0,
        2410.0,
        2410.0,
        2410.0,
        2410.0,
        2410.0,
        2410.0,
        2410.0,
        2410.0,
        2410.0,
        2410.0,
        2410.0,
        2410.0,
        2405.0,
        2405.0,
        2405.0,
        2405.0,
        2405.0,
        2405.0,
        2405.0,
        2415.0,
        2415.0,
        2415.0,
        2415.0,
        2415.0,
        2420.0,
        2420.0,
        2420.0,
        2420.0,
        2420.0,
        2420.0,
        2420.0,
        2420.0,
        2415.0,
        2415.0,
        2415.0,
        2420.0,
        2415.0,
        2415.0,
        2415.0,
        2415.0,
        2415.0,
        2415.0,
        2415.0,
        2415.0,
        2415.0,
        2415.0,
        2415.0,
        2415.0,
        2415.0,
        2415.0,
        2415.0,
        2415.0,
        2415.0,
        2410.0,
        2410.0,
        2410.0,
        2410.0,
        2410.0,
        2410.0,
        2415.0,
        2410.0,
        2410.0,
        2415.0,
        2415.0,
        2410.0,
        2410.0,
        2415.0,
        2415.0,
        null,
        null,
        null,
        null,
        null,
        2390.0
      ],
      "low": [
        2435.0,
        2435.0,
        2435.0,
        2435.0,
        2435.0,
        2425.0,
        2425.0,
        2430.0,
        2430.0,
        2430.0,
        2430.0,
        2430.0,
        2430.0,
        2430.0,
        2430.0,
        2430.0,
        2430.0,
        2430.0,
        2430.0,
        2430.0,
        2425.0,
        2425.0,
        2425.0,
        2425.0,
        2425.0,
        2430.0,
        2430.0,
        2430.0,
        2425.0,
        2425.0,
        2425.0,
        2425.0,
        2425.0,
        2425.0,
        2425.0,
        2425.0,
        2425.0,
        2425.0,
        2425.0,
        2425.0,
        2420.0,
        2420.0,
        2420.0,
        2420.0,
        2420.0,
        2415.0,
        2415.0,
        2415.0,
        2415.0,
        2420.0,
        2425.0,
        2425.0,
        2425.0,
        2425.0,
        2425.0,
        2430.0,
        2430.0,
        2430.0,
        2430.0,
        2430.0,
        2430.0,
        2430.0,
        2430.0,
        2430.0,
        2425.0,
        2425.0,
        2425.0,
        2420.0,
        2420.0,
        2420.0,
        2420.0,
        2420.0,
        2420.0,
        2420.0,
        2420.0,
        2420.0,
        2420.0,
        2420.0,
        2420.0,
        2420.0,
        2420.0,
        2420.0,
        2420.0,
        2420.0,
        2420.0,
        2420.0,
        2415.0,
        2415.0,
        2415.0,
        2420.0,
        2420.0,
        2420.0,
        2420.0,
        2420.0,
        2420.0,
        2420.0,
        2420.0,
        2420.0,
        2420.0,
        2420.0,
        2420.0,
        2415.0,
        2415.0,
        2415.0,
        2415.0,
        2415.0,
        2415.0,
        2415.0,
        2415.0,
        2410.0,
        2410.0,
        2410.0,
        2410.0,
        2410.0,
        2410.0,
        2410.0,
        2410.0,
        2410.0,
        2410.0,
        2410.0,
        2410.0,
        2410.0,
        2405.0,
        2405.0,
        2405.0,
        2405.0,
        2405.0,
        2405.0,
        2405.0,
        2405.0,
        2405.0,
        2410.0,
        2410.0,
        2410.0,
        2410.0,
        2410.0,
        2410.0,
        2410.0,
        2410.0,
        2410.0,
        2410.0,
        2410.0,
        2410.0,
        2410.0,
        2410.0,
        2410.0,
        2410.0,
        2410.0,
        2410.0,
        2410.0,
        2410.0,
        2410.0,
        2410.0,
        2410.0,
        2410.0,
        2410.0,
        2410.0,
        2410.0,
        2410.0,
        2410.0,
        2410.0,
        2410.0,
        2410.0,
        2410.0,
        2410.0,
        2410.0,
        2410.0,
        2410.0,
        2410.0,
        2410.0,
        2410.0,
        2410.0,
        2410.0,
        2410.0,
        2410.0,
        2410.0,
        2410.0,
        2410.0,
        2410.0,
        2410.0,
        2410.0,
        2410.0,
        2410.0,
        2410.0,
        2410.0,
        2405.0,
        2405.0,
        2405.0,
        2405.0,
        2405.0,
        2405.0,
        2405.0,
        2405.0,
        2405.0,
        2405.0,
        2405.0,
        2405.0,
        2405.0,
        2405.0,
        2405.0,
        2405.0,
        2405.0,
        2405.0,
        2405.0,
        2405.0,
        2405.0,
        2405.0,
        2405.0,
        2400.0,
        2400.0,
        2400.0,
        2400.0,
        2400.0,
        2400.0,
        2400.0,
        2400.0,
        2400.0,
        2410.0,
        2410.0,
        2410.0,
        2410.0,
        2410.0,
        2415.0,
        2415.0,
        2415.0,
        2410.0,
        2410.0,
        2410.0,
        2410.0,
        2410.0,
        2410.0,
        2410.0,
        2410.0,
        2410.0,
        2410.0,
        2410.0,
        2410.0,
        2410.0,
        2410.0,
        2410.0,
        2410.0,
        2410.0,
        2410.0,
        2410.0,
        2410.0,
        2410.0,
        2410.0,
        2405.0,
        2405.0,
        2405.0,
        2405.0,
        2405.0,
        2405.0,
        2405.0,
        2405.0,
        2405.0,
        2405.0,
        2405.0,
        2405.0,
        2405.0,
        2405.0,
        2405.0,
        2405.0,
        2405.0,
        2410.0,
        null,
        null,
        null,
        null,
        null,
        2390.0
      ],
      "close": [
        2445.0,
        2440.0,
        2440.0,
        2440.0,
        2435.0,
        2430.0,
        2435.0,
        2435.0,
        2435.0,
        2435.0,
        2435.0,
        2435.0,
        2435.0,
        2435.0,
        2430.0,
        2435.0,
        2430.0,
        2430.0,
        2435.0,
        2430.0,
        2430.0,
        2430.0,
        2425.0,
        2430.0,
        2435.0,
        2430.0,
        2435.0,
        2430.0,
        2430.0,
        2425.0,
        2425.0,
        2430.0,
        2425.0,
        2425.0,
        2425.0,
        2425.0,
        2425.0,
        2430.0,
        2425.0,
        2430.0,
        2420.0,
        2420.0,
        2420.0,
        2420.0,
        2420.0,
        2420.0,
        2420.0,
        2415.0,
        2420.0,
        2430.0,
        2430.0,
        2430.0,
        2430.0,
        2430.0,
        2435.0,
        2435.0,
        2435.0,
        2435.0,
        2435.0,
        2435.0,
        2430.0,
        2435.0,
        2430.0,
        2435.0,
        2425.0,
        2425.0,
        2425.0,
        2425.0,
        2420.0,
        2425.0,
        2425.0,
        2425.0,
        2425.0,
        2425.0,
        2420.0,
        2420.0,
        2420.0,
        2425.0,
        2425.0,
        2420.0,
        2425.0,
        2420.0,
        2420.0,
        2420.0,
        2420.0,
        2420.0,
        2415.0,
        2420.0,
        2420.0,
        2425.0,
        2420.0,
        2420.0,
        2425.0,
        2420.0,
        2425.0,
        2425.0,
        2420.0,
        2425.0,
        2420.0,
        2420.0,
        2420.0,
        2415.0,
        2415.0,
        2420.0,
        2420.0,
        2415.0,
        2415.0,
        2420.0,
        2415.0,
        2410.0,
        2410.0,
        2410.0,
        2410.0,
        2415.0,
        2410.0,
        2410.0,
        2410.0,
        2410.0,
        2410.0,
        2415.0,
        2410.0,
        2410.0,
        2405.0,
        2405.0,
        2405.0,
        2405.0,
        2405.0,
        2405.0,
        2405.0,
        2410.0,
        2415.0,
        2415.0,
        2415.0,
        2410.0,
        2410.0,
        2415.0,
        2415.0,
        2415.0,
        2415.0,
        2410.0,
        2410.0,
        2410.0,
        2410.0,
        2410.0,
        2410.0,
        2410.0,
        2410.0,
        2410.0,
        2410.0,
        2415.0,
        2410.0,
        2415.0,
        2415.0,
        2410.0,
        2415.0,
        2410.0,
        2410.0,
        2410.0,
        2410.0,
        2415.0,
        2410.0,
        2415.0,
        2410.0,
        2410.0,
        2415.0,
        2415.0,
        2410.0,
        2410.0,
        2410.0,
        2410.0,
        2410.0,
        2410.0,
        2415.0,
        2410.0,
        2415.0,
        2410.0,
        2410.0,
        2410.0,
        2410.0,
        2410.0,
        2410.0,
        2410.0,
        2415.0,
        2415.0,
        2410.0,
        2405.0,
        2405.0,
        2405.0,
        2410.0,
        2410.0,
        2405.0,
        2405.0,
        2410.0,
        2410.0,
        2405.0,
        2410.0,
        2410.0,
        2405.0,
        2410.0,
        2405.0,
        2405.0,
        2405.0,
        2405.0,
        2405.0,
        2405.0,
        2405.0,
        2410.0,
        2405.0,
        2400.0,
        2400.0,
        2405.0,
        2400.0,
        2400.0,
        2400.0,
        2405.0,
        2405.0,
        2415.0,
        2410.0,
        2415.0,
        2415.0,
        2415.0,
        2420.0,
        2415.0,
        2415.0,
        2420.0,
        2415.0,
        2415.0,
        2420.0,
        2415.0,
        2415.0,
        2415.0,
        2415.0,
        2415.0,
        2415.0,
        2410.0,
        2415.0,
        2415.0,
        2415.0,
        2415.0,
        2415.0,
        2415.0,
        2415.0,
        2415.0,
        2415.0,
        2410.0,
        2415.0,
        2415.0,
        2410.0,
        2410.0,
        2410.0,
        2410.0,
        2410.0,
        2405.0,
        2410.0,
        2410.0,
        2405.0,
        2410.0,
        2410.0,
        2410.0,
        2410.0,
        2410.0,
        2410.0,
        2405.0,
        2415.0,
        2410.0,
        null,
        null,
        null,
        null,
        null,
        2390.0
      ],
      "volume": [
        0,
        1027000,
        263000,
        452000,
        468000,
        1612000,
        286000,
        97000,
        178000,
        196000,
        724174,
        245008,
        93168,
        278762,
        80873,
        120907,
        108452,
        76083,
        93371,
        548063,
        296102,
        296002,
        220555,
        167936,
        375246,
        85282,
        115085,
        87167,
        786651,
        466300,
        149331,
        105973,
        88378,
        79478,
        73904,
        103462,
        97337,
        127871,
        99616,
        123811,
        2030252,
        414448,
        141527,
        182648,
        444478,
        447792,
        95812,
        82125,
        726823,
        169765,
        41794,
        64892,
        89438,
        100542,
        157605,
        50840,
        65247,
        81585,
        76407,
        40847,
        65651,
        76461,
        37368,
        54311,
        493647,
        111807,
        141155,
        262651,
        99002,
        56362,
        37130,
        45659,
        28458,
        50903,
        91545,
        32448,
        100172,
        144772,
        123584,
        105107,
        79994,
        102366,
        152595,
        147205,
        324746,
        55618,
        417278,
        259251,
        253531,
        24562,
        25083,
        32675,
        23556,
        63831,
        151679,
        25841,
        39088,
        60068,
        124181,
        91157,
        62350,
        258472,
        328637,
        83625,
        74188,
        50629,
        102348,
        140911,
        363410,
        754661,
        382306,
        132447,
        353637,
        208495,
        127602,
        102409,
        81935,
        40522,
        153322,
        157098,
        154187,
        149784,
        548133,
        166382,
        142702,
        96740,
        105453,
        494063,
        174452,
        119825,
        468609,
        33107,
        32295,
        50385,
        46781,
        49248,
        259860,
        173568,
        45693,
        43195,
        37381,
        158731,
        119032,
        71840,
        290667,
        43193,
        53362,
        114822,
        41163,
        44240,
        47059,
        29042,
        38506,
        39509,
        63169,
        46384,
        41297,
        33910,
        47487,
        36735,
        58540,
        48890,
        56940,
        35885,
        34289,
        58035,
        44802,
        32994,
        36652,
        69051,
        74435,
        38142,
        40096,
        48170,
        46544,
        48003,
        111075,
        46604,
        29001,
        93601,
        57261,
        26969,
        26092,
        46579,
        38566,
        1102232,
        206368,
        182191,
        42585,
        42224,
        28023,
        35188,
        32883,
        39354,
        35318,
        25373,
        52289,
        27006,
        84611,
        69483,
        66424,
        51853,
        56037,
        150128,
        67465,
        55034,
        91473,
        83272,
        893580,
        369919,
        138808,
        98468,
        44868,
        57907,
        60448,
        54970,
        1075899,
        276647,
        265486,
        46347,
        95936,
        97019,
        45652,
        46032,
        53137,
        272850,
        67313,
        59813,
        81317,
        70543,
        43606,
        64044,
        80734,
        67848,
        145267,
        111084,
        70098,
        65223,
        67882,
        340414,
        82607,
        104607,
        89228,
        62061,
        116603,
        100776,
        135917,
        979097,
        280499,
        156553,
        102455,
        187367,
        83170,
        115202,
        108451,
        119089,
        323664,
        140631,
        332541,
        117720,
        573928,
        275381,
        182691,
        170660,
        1795491,
        null,
        null,
        null,
        null,
        null,
        0
      ],
      "adjclose": []
    },
    "raw_meta": {
      "currency": "TWD",
      "symbol": "2330.TW",
      "exchangeName": "TAI",
      "fullExchangeName": "Taiwan",
      "instrumentType": "EQUITY",
      "firstTradeDate": 946947600,
      "regularMarketTime": 1782279008,
      "hasPrePostMarketData": false,
      "gmtoffset": 28800,
      "timezone": "CST",
      "exchangeTimezoneName": "Asia/Taipei",
      "regularMarketPrice": 2390.0,
      "fiftyTwoWeekHigh": 2535.0,
      "fiftyTwoWeekLow": 1055.0,
      "regularMarketDayHigh": 2445.0,
      "regularMarketDayLow": 2390.0,
      "regularMarketVolume": 65632286,
      "longName": "Taiwan Semiconductor Manufacturing Company Limited",
      "shortName": "TAIWAN SEMICONDUCTOR MANUFACTUR",
      "chartPreviousClose": 2490.0,
      "previousClose": 2490.0,
      "scale": 3,
      "priceHint": 2,
      "currentTradingPeriod": {
        "pre": {
          "timezone": "CST",
          "start": 1782262800,
          "end": 1782262800,
          "gmtoffset": 28800
        },
        "regular": {
          "timezone": "CST",
          "start": 1782262800,
          "end": 1782279000,
          "gmtoffset": 28800
        },
        "post": {
          "timezone": "CST",
          "start": 1782279000,
          "end": 1782279000,
          "gmtoffset": 28800
        }
      },
      "tradingPeriods": [
        [
          {
            "timezone": "CST",
            "start": 1782262800,
            "end": 1782279000,
            "gmtoffset": 28800
          }
        ]
      ],
      "dataGranularity": "1m",
      "range": "1d",
      "validRanges": [
        "1d",
        "5d",
        "1mo",
        "3mo",
        "6mo",
        "1y",
        "2y",
        "5y",
        "10y",
        "ytd",
        "max"
      ]
    },
    "unmapped_meta_fields": {
      "fullExchangeName": "Taiwan",
      "instrumentType": "EQUITY",
      "hasPrePostMarketData": false,
      "fiftyTwoWeekHigh": 2535.0,
      "fiftyTwoWeekLow": 1055.0,
      "regularMarketDayHigh": 2445.0,
      "regularMarketDayLow": 2390.0,
      "regularMarketVolume": 65632286,
      "longName": "Taiwan Semiconductor Manufacturing Company Limited",
      "shortName": "TAIWAN SEMICONDUCTOR MANUFACTUR"
    }
  },
  "freshness_status": "realtime_candidate",
  "staleness_seconds": 14913,
  "delay_status": "delayed",
  "requires_auth": false,
  "requires_session": false,
  "risk_level": "medium",
  "risk_notes": [
    "Rate limits apply",
    "Not an official data source",
    "Unofficial endpoint"
  ],
  "ai_suitability": "live_watchlist",
  "is_usable_now": true,
  "potentially_usable_with_credentials": false,
  "unsupported_targets": [],
  "failed_targets": [],
  "warnings": [],
  "errors": []
}